tsingpig_lab/__init__.py
tsingpig_lab/tsingpig_lab.py
TsingPig_Lab-0.0.2.dist-info/LICENSE
TsingPig_Lab-0.0.2.dist-info/METADATA
TsingPig_Lab-0.0.2.dist-info/WHEEL
TsingPig_Lab-0.0.2.dist-info/top_level.txt
TsingPig_Lab-0.0.2.dist-info/RECORD
