Metadata-Version: 2.1
Name: TsingPig-Lab
Version: 0.0.2
Summary: TsingPig_Lab is a package for algorithm.
Home-page: https://gitlab.com/tsingpig-code/tsingpig_lab
Author: tsingpig
Author-email: 1114196607@qq.com
License: UNKNOWN
Platform: UNKNOWN
Classifier: Programming Language :: Python :: 3
Classifier: License :: OSI Approved :: MIT License
Classifier: Operating System :: OS Independent
Requires-Dist: math
